skpsl/__init__.py
skpsl/estimators/__init__.py
skpsl/estimators/probabilistic_scoring_list.py
skpsl/estimators/probabilistic_scoring_system.py
skpsl/helper/__init__.py
skpsl/helper/binarization_optimizers.py
skpsl/helper/calibrators/__init__.py
skpsl/helper/calibrators/beta_transform.py
skpsl/helper/calibrators/sigmoid_transform.py
skpsl/metrics/__init__.py
skpsl/metrics/expected_entropy.py
skpsl/metrics/precision_at_recall_k.py
skpsl/metrics/soft_rankingloss.py
skpsl/metrics/wloss.py
skpsl/preprocessing/__init__.py
skpsl/preprocessing/binarizer.py
scikit_psl-0.7.2.dist-info/LICENSE
scikit_psl-0.7.2.dist-info/METADATA
scikit_psl-0.7.2.dist-info/WHEEL
scikit_psl-0.7.2.dist-info/RECORD
