Metadata-Version: 2.1
Name: scikit-psl
Version: 0.7.2
Summary: Probabilistic Scoring List classifier
Home-page: https://github.com/trr318/scikit-psl
License: MIT
Author: Stefan Heid
Author-email: stefan.heid@upb.de
Requires-Python: >=3.10,<3.13
Classifier: License :: OSI Approved :: MIT License
Classifier: Programming Language :: Python :: 3
Classifier: Programming Language :: Python :: 3.10
Classifier: Programming Language :: Python :: 3.11
Classifier: Programming Language :: Python :: 3.12
Requires-Dist: joblib (>=1.4.2,<2.0.0)
Requires-Dist: numpy (>=1.26.4,<2.0.0)
Requires-Dist: pandas (>=2.2.3,<3.0.0)
Requires-Dist: scikit-learn (>=1.5.2,<2.0.0)
Requires-Dist: scipy (>=1.14.1,<2.0.0)
Requires-Dist: sortedcontainers (>=2.4.0,<3.0.0)
Project-URL: Repository, https://github.com/trr318/scikit-psl
